{
  "posts": [
    { "body": "Talala", "author": "TTT", "id": "0.9520620516656315" },
    { "body": "Tung Tung Tung", "author": "Sahu", "id": "0.0492148377442172" },
    { "body": "Very Good!", "author": "LungTu", "id": "0.6600038367869299" },
    { "body": "Good Job!", "author": "BBB", "id": "0.3777218466106498" },
    { "body": "Nice", "author": "Boon", "id": "0.4852477482646218" },
    {
      "body": "This course is hopefully very helpful to you!",
      "author": "Maximilian",
      "id": "0.3852385742646235"
    }
  ]
}
